pystencils/__init__.py
pystencils/_version.py
pystencils/alignedarray.py
pystencils/assignment.py
pystencils/astnodes.py
pystencils/bit_masks.py
pystencils/cache.py
pystencils/config.py
pystencils/display_utils.py
pystencils/enums.py
pystencils/fast_approximation.py
pystencils/field.py
pystencils/functions.py
pystencils/integer_functions.py
pystencils/integer_set_analysis.py
pystencils/jupyter.py
pystencils/kernel_contrains_check.py
pystencils/kernel_decorator.py
pystencils/kernel_wrapper.py
pystencils/kernelcreation.py
pystencils/node_collection.py
pystencils/placeholder_function.py
pystencils/plot.py
pystencils/rng.py
pystencils/session.py
pystencils/simplificationfactory.py
pystencils/slicing.py
pystencils/spatial_coordinates.py
pystencils/stencil.py
pystencils/sympyextensions.py
pystencils/timeloop.py
pystencils/transformations.py
pystencils/utils.py
pystencils/backends/__init__.py
pystencils/backends/arm_instruction_sets.py
pystencils/backends/cbackend.py
pystencils/backends/cuda_backend.py
pystencils/backends/dot.py
pystencils/backends/json.py
pystencils/backends/ppc_instruction_sets.py
pystencils/backends/riscv_instruction_sets.py
pystencils/backends/simd_instruction_sets.py
pystencils/backends/x86_instruction_sets.py
pystencils/boundaries/__init__.py
pystencils/boundaries/boundaryconditions.py
pystencils/boundaries/boundaryhandling.py
pystencils/boundaries/createindexlist.py
pystencils/boundaries/createindexlistcython.pyx
pystencils/boundaries/inkernel.py
pystencils/cpu/__init__.py
pystencils/cpu/cpujit.py
pystencils/cpu/kernelcreation.py
pystencils/cpu/msvc_detection.py
pystencils/cpu/vectorization.py
pystencils/datahandling/__init__.py
pystencils/datahandling/blockiteration.py
pystencils/datahandling/datahandling_interface.py
pystencils/datahandling/parallel_datahandling.py
pystencils/datahandling/serial_datahandling.py
pystencils/datahandling/vtk.py
pystencils/fd/__init__.py
pystencils/fd/derivation.py
pystencils/fd/derivative.py
pystencils-1.4.dist-info/licenses/LICENSE
pystencils-1.4.dist-info/METADATA
pystencils-1.4.dist-info/WHEEL
pystencils-1.4.dist-info/top_level.txt
pystencils-1.4.dist-info/RECORD
