Metadata-Version: 2.4
Name: pystencils
Version: 1.4
Summary: Speeding up stencil computations on CPUs and GPUs
Author: Martin Bauer, Jan Hönig , Markus Holzer, Frederik Hennig
Author-email: cs10-codegen@fau.de
License-Expression: GPL-3.0-or-later
Project-URL: Bug Tracker, https://i10git.cs.fau.de/pycodegen/pystencils/-/issues
Project-URL: Documentation, https://pycodegen.pages.i10git.cs.fau.de/pystencils/
Project-URL: Source Code, https://i10git.cs.fau.de/pycodegen/pystencils
Classifier: Development Status :: 4 - Beta
Classifier: Framework :: Jupyter
Classifier: Topic :: Software Development :: Code Generators
Classifier: Topic :: Scientific/Engineering :: Physics
Classifier: Intended Audience :: Developers
Classifier: Intended Audience :: Science/Research
Requires-Python: >=3.10
License-File: LICENSE
Requires-Dist: sympy<=1.12.1,>=1.9
Requires-Dist: numpy>=1.8.0
Requires-Dist: appdirs
Requires-Dist: joblib
Requires-Dist: pyyaml
Requires-Dist: fasteners
Provides-Extra: gpu
Requires-Dist: cupy; extra == "gpu"
Provides-Extra: alltrafos
Requires-Dist: islpy; extra == "alltrafos"
Requires-Dist: py-cpuinfo; extra == "alltrafos"
Provides-Extra: bench-db
Requires-Dist: blitzdb; extra == "bench-db"
Requires-Dist: pymongo; extra == "bench-db"
Requires-Dist: pandas; extra == "bench-db"
Provides-Extra: interactive
Requires-Dist: matplotlib; extra == "interactive"
Requires-Dist: ipy_table; extra == "interactive"
Requires-Dist: imageio; extra == "interactive"
Requires-Dist: jupyter; extra == "interactive"
Requires-Dist: pyevtk; extra == "interactive"
Requires-Dist: rich; extra == "interactive"
Requires-Dist: graphviz; extra == "interactive"
Provides-Extra: use-cython
Requires-Dist: Cython; extra == "use-cython"
Provides-Extra: doc
Requires-Dist: sphinx; extra == "doc"
Requires-Dist: sphinx_rtd_theme; extra == "doc"
Requires-Dist: nbsphinx; extra == "doc"
Requires-Dist: sphinxcontrib-bibtex; extra == "doc"
Requires-Dist: sphinx_autodoc_typehints; extra == "doc"
Requires-Dist: pandoc; extra == "doc"
Provides-Extra: tests
Requires-Dist: pytest; extra == "tests"
Requires-Dist: pytest-cov; extra == "tests"
Requires-Dist: pytest-html; extra == "tests"
Requires-Dist: ansi2html; extra == "tests"
Requires-Dist: pytest-xdist; extra == "tests"
Requires-Dist: flake8; extra == "tests"
Requires-Dist: nbformat; extra == "tests"
Requires-Dist: nbconvert; extra == "tests"
Requires-Dist: ipython; extra == "tests"
Requires-Dist: matplotlib; extra == "tests"
Requires-Dist: py-cpuinfo; extra == "tests"
Requires-Dist: randomgen>=1.18; extra == "tests"
Dynamic: license-file
